fiasco/CITATION.rst
fiasco/__init__.py
fiasco/base.py
fiasco/collections.py
fiasco/conftest.py
fiasco/elements.py
fiasco/fiasco.py
fiasco/gaunt.py
fiasco/ions.py
fiasco/levels.py
fiasco/version.py
fiasco/data/nikolic_table_2.dat
fiasco/data/nikolic_table_5.dat
fiasco/io/__init__.py
fiasco/io/datalayer.py
fiasco/io/factory.py
fiasco/io/generic.py
fiasco/io/sources/__init__.py
fiasco/io/sources/continuum_sources.py
fiasco/io/sources/ion_sources.py
fiasco/io/sources/non_ion_sources.py
fiasco/io/sources/tests/__init__.py
fiasco/io/sources/tests/test_sources.py
fiasco/io/tests/__init__.py
fiasco/io/tests/test_datalayer.py
fiasco/tests/__init__.py
fiasco/tests/test_base.py
fiasco/tests/test_collections.py
fiasco/tests/test_element.py
fiasco/tests/test_fiasco.py
fiasco/tests/test_gaunt.py
fiasco/tests/test_ion.py
fiasco/tests/data/file_hashes_v10.1.json
fiasco/tests/data/file_hashes_v11.0.2.json
fiasco/tests/data/file_hashes_v8.0.7.json
fiasco/tests/data/file_hashes_v9.0.1.json
fiasco/tests/data/test_file_list.json
fiasco/tests/idl/__init__.py
fiasco/tests/idl/conftest.py
fiasco/tests/idl/helpers.py
fiasco/tests/idl/test_idl_continuum.py
fiasco/tests/idl/test_idl_goft.py
fiasco/tests/idl/test_idl_ioneq.py
fiasco/tests/idl/test_idl_level_pops.py
fiasco/tests/idl/data/dielectronic_recombination_suppression_factor_14_4_v10.1.0.asdf
fiasco/tests/idl/data/dielectronic_recombination_suppression_factor_14_4_v11.0.2.asdf
fiasco/tests/idl/data/dielectronic_recombination_suppression_factor_16_5_v10.1.0.asdf
fiasco/tests/idl/data/dielectronic_recombination_suppression_factor_16_5_v11.0.2.asdf
fiasco/tests/idl/data/dielectronic_recombination_suppression_factor_26_12_v10.1.0.asdf
fiasco/tests/idl/data/dielectronic_recombination_suppression_factor_26_12_v11.0.2.asdf
fiasco/tests/idl/data/dielectronic_recombination_suppression_factor_26_13_v10.1.0.asdf
fiasco/tests/idl/data/dielectronic_recombination_suppression_factor_26_13_v11.0.2.asdf
fiasco-0.7.0.dist-info/licenses/LICENSE.rst
fiasco-0.7.0.dist-info/METADATA
fiasco-0.7.0.dist-info/WHEEL
fiasco-0.7.0.dist-info/top_level.txt
fiasco-0.7.0.dist-info/RECORD
