Metadata-Version: 2.4
Name: fiasco
Version: 0.7.0
Summary: A Python interface to the CHIANTI atomic database
Author-email: Will Barnes <will.t.barnes@gmail.com>
License: Copyright (c) 2024, Will Barnes
Project-URL: Homepage, https://fiasco.readthedocs.io
Project-URL: Documentation, https://fiasco.readthedocs.io
Project-URL: Repository, https://github.com/wtbarnes/fiasco
Project-URL: Issues, https://github.com/wtbarnes/fiasco/issues/
Keywords: heliophysics,solar physics,astrophysics,plasma physics,science,atomic data,atomic physics
Classifier: Development Status :: 4 - Beta
Classifier: Intended Audience :: Science/Research
Classifier: License :: OSI Approved :: BSD License
Classifier: Operating System :: OS Independent
Classifier: Programming Language :: Python :: 3
Classifier: Programming Language :: Python :: 3.12
Classifier: Programming Language :: Python :: 3.13
Classifier: Programming Language :: Python :: 3.14
Classifier: Programming Language :: Python :: Implementation :: CPython
Classifier: Topic :: Scientific/Engineering :: Physics
Classifier: Topic :: Scientific/Engineering :: Astronomy
Requires-Python: >=3.12
License-File: LICENSE.rst
Requires-Dist: astropy>=5.2
Requires-Dist: fortranformat>=2
Requires-Dist: h5py>=3.9
Requires-Dist: numpy<2.3.0,>=1.25
Requires-Dist: plasmapy>=2024.10.0
Provides-Extra: all
Requires-Dist: fiasco; extra == "all"
Provides-Extra: test
Requires-Dist: fiasco[all]; extra == "test"
Requires-Dist: asdf-astropy>=0.5; extra == "test"
Requires-Dist: asdf>=3.1; extra == "test"
Requires-Dist: matplotlib>=3.8; extra == "test"
Requires-Dist: pytest-astropy>=0.11; extra == "test"
Requires-Dist: pytest-cov>=5; extra == "test"
Requires-Dist: pytest>=8; extra == "test"
Provides-Extra: test-idl
Requires-Dist: fiasco[test]; extra == "test-idl"
Requires-Dist: hissw>=2.3; extra == "test-idl"
Requires-Dist: GitPython>=3.1.34; extra == "test-idl"
Provides-Extra: docs
Requires-Dist: fiasco[all]; extra == "docs"
Requires-Dist: aiapy>=0.11; extra == "docs"
Requires-Dist: asdf-astropy>=0.5; extra == "docs"
Requires-Dist: asdf>=3.1; extra == "docs"
Requires-Dist: hissw>=2.3; extra == "docs"
Requires-Dist: pydata-sphinx-theme>=0.16; extra == "docs"
Requires-Dist: sphinx-automodapi>=0.16; extra == "docs"
Requires-Dist: sphinx-design>=0.5; extra == "docs"
Requires-Dist: sphinx-gallery>0.14; extra == "docs"
Requires-Dist: sphinx>=8; extra == "docs"
Requires-Dist: sphinxcontrib-bibtex>=2.6; extra == "docs"
Provides-Extra: dev
Requires-Dist: fiasco[docs,test]; extra == "dev"
Dynamic: license-file
